{
  "scene_id": "V2-E02-S02",
  "status": "pass",
  "checks": {
    "objective": true,
    "state_transition": true,
    "owned_elements": true,
    "reveal_order": true,
    "canon": true,
    "continuity": true,
    "prose_quality": true
  },
  "issues": [],
  "reason": "산문이 장면의 목표인 '공허수들의 습격'과 '리안의 저장 능력이 괴물들을 자극함'을 충실하게 묘사하였습니다. 시작 상태(폐기 구역 진입)에서 종료 상태(공허수들의 갈망으로 인한 공포 경험)로의 전이가 매끄럽게 이루어졌으며, 직전 승인 산문에서 제시된 '위원회 설계' 및 '회로' 설정을 일관성 있게 유지하며 서사를 확장했습니다. 미래 금지 요소인 C13(살아있는 저장소의 정체)이나 EL_Vessel_Awareness(자각)의 핵심 결론을 미리 도출하지 않고, 현재 가용한 설정(EL_Vessel_Circuit)의 물리적 반응으로만 묘사하여 reveal_order를 준수하였습니다.",
  "prose_sha256": "afe69eabbd43036d96eb027ed85c17133095b426ea64c93ecb6d4527ba9d1100",
  "scene_contract_sha256": "77908654a603badbb93c59a72bd49ca0d55ba3d8e3a0e0bba2f056c66073a1a8"
}
